shopify_multipass/__init__.py
shopify_multipass/_version.py
shopify_multipass/multipass.py
shopify_multipass/py.typed
shopify_multipass_auth-0.1.1.dist-info/licenses/LICENSE
shopify_multipass_auth-0.1.1.dist-info/METADATA
shopify_multipass_auth-0.1.1.dist-info/WHEEL
shopify_multipass_auth-0.1.1.dist-info/top_level.txt
shopify_multipass_auth-0.1.1.dist-info/RECORD
