Metadata-Version: 2.4
Name: shopify-multipass-auth
Version: 0.1.1
Summary: A Python library for generating Shopify multipass tokens for customer authentication
Home-page: https://github.com/autonomous-tech/shopify-multipass-auth
Author: Usama Mashood
Author-email: Usama Mashood <usama@autonomoustech.ca>
Maintainer-email: Usama Mashood <usama@autonomoustech.ca>
License: MIT License
Project-URL: Homepage, https://github.com/autonomous-tech/shopify-multipass-auth
Project-URL: Documentation, https://github.com/autonomous-tech/shopify-multipass-auth#readme
Project-URL: Repository, https://github.com/autonomous-tech/shopify-multipass-auth
Project-URL: Bug Tracker, https://github.com/autonomous-tech/shopify-multipass-auth/issues
Keywords: shopify,multipass,authentication,ecommerce
Classifier: Development Status :: 4 - Beta
Classifier: Intended Audience :: Developers
Classifier: License :: OSI Approved :: MIT License
Classifier: Programming Language :: Python :: 3
Classifier: Programming Language :: Python :: 3.7
Classifier: Programming Language :: Python :: 3.8
Classifier: Programming Language :: Python :: 3.9
Classifier: Programming Language :: Python :: 3.10
Classifier: Programming Language :: Python :: 3.11
Classifier: Programming Language :: Python :: 3.12
Classifier: Topic :: Software Development :: Libraries :: Python Modules
Classifier: Topic :: Internet :: WWW/HTTP
Classifier: Topic :: Security :: Cryptography
Classifier: Operating System :: OS Independent
Requires-Python: >=3.7
License-File: LICENSE
Requires-Dist: pycryptodome>=3.20.0
Dynamic: author
Dynamic: home-page
Dynamic: license-file
Dynamic: requires-python
